scida_utils/__init__.py
scida_utils/eda.cp310-win_amd64.pyd
scida_utils-0.2.17.dist-info/METADATA
scida_utils-0.2.17.dist-info/WHEEL
scida_utils-0.2.17.dist-info/top_level.txt
scida_utils-0.2.17.dist-info/RECORD
