Metadata-Version: 2.1
Name: scida-utils
Version: 0.2.17
Summary: scida_utils
Home-page: 
Download-URL: 
Author: sike6054
Author-email: sike6054@gmail.com
Classifier: Programming Language :: Python :: 3.10
Classifier: Operating System :: Microsoft :: Windows
Requires-Python: >=3.10, <3.11
